{
  "nav": [
    "图书",
    "童书",
    "电子书",
    "听书",
    "网络文学",
    "创意文具",
    "艺术品",
    "女装",
    "男装",
    "男女鞋",
    "童装童鞋",
    "内衣配饰",
    "母婴玩具",
    "食品生鲜",
    "美妆个护",
    "手机数码",
    "电脑办公",
    "家用电器",
    "运动户外",
    "珠宝饰品",
    "箱包皮具",
    "当当优品",
    "家居家纺",
    "营养保健",
    "手表眼镜",
    "汽车用品",
    "家具家装",
    "当当礼品卡",
    "猜您喜欢"
  ],
  "book": [
    {
      "pic": "static/img/m1.jpg",
      "name": "总榜"
    },
    {
      "pic": "static/img/m2.jpg",
      "name": "新书榜"
    },
    {
      "pic": "static/img/m3.jpg",
      "name": "童书榜"
    },
    {
      "pic": "static/img/m4.jpg",
      "name": "人气榜"
    },
    {
      "pic": "static/img/m5.jpg",
      "name": "畅销榜"
    },
    {
      "pic": "static/img/m6.jpg",
      "name": "成人榜"
    }
  ],
  "theme": {
    "fiction": [
      [
        "小说"
      ],
      [
        "社会",
        "侦探/悬疑/推理",
        "情感",
        "世界名著",
        "历史",
        "科幻",
        "惊悚/恐怖",
        "武侠",
        "官场",
        "军事",
        "都市",
        "乡土",
        "职场",
        "财经",
        "影视小说",
        "四大名著",
        "中国古典小说",
        "外国小说",
        "中国当代小说",
        "作品集"
      ]
    ],
    "letter": [
      [
        "文学"
      ],
      [
        "现当代随笔",
        "名家作品",
        "文集",
        "纪实文学",
        "中国古诗词",
        "现当代诗歌",
        "外国诗歌",
        "古代随笔",
        "外国随笔",
        "民间文学",
        "戏剧"
      ]
    ],
    "mem": [
      [
        "传记"
      ],
      [
        "文学家",
        "政治人物",
        "女性人物",
        "财经人物",
        "历史人物",
        "影视明星",
        "领袖首脑",
        "艺术家",
        "科学家",
        "体育明星",
        "法律人物",
        "历代帝王",
        "自传",
        "任务集合",
        "画传",
        "社会学家",
        "学者",
        "国学大师",
        "军事人物",
        "宗教人物",
        "哲学家",
        "教育家",
        "年谱"
      ]
    ],
    "art":[
      ["艺术"],
      ["绘画","书法/篆刻","音乐","摄影","设计","收藏/鉴赏","艺术理论","小人书","媒体艺术","艺术概况","人体艺术","工艺美术","戏剧艺术","民间艺术","建筑艺术","舞蹈","雕塑"]
    ],
    "usb":[
      ["童书"],
      ["0-2岁","3-6岁","7-10岁","11-14岁","科普/百科","外国儿童文学","中国儿童文学","绘本","玩具书","婴儿读物","少儿英语","励志/成长","动漫/卡通","幼儿启蒙","进口儿童书","益智游戏","少儿期刊","阅读工具书","少儿影视","少儿音乐"]
    ],
    "liter":[
      ["青春文学"],
      ["爱情/情感","玄幻/新武侠/科幻","古代言情","穿越/重生","校园","影视写真","叛逆/成长","娱乐/偶像","魔幻","悬疑/惊悚","爆笑/无厘头"]
    ],
    "anime":[
      ["动漫/幽默"],
      ["大陆动漫","欧美动漫","港台漫画","日韩动漫","幽默/笑话集","画集","动漫学堂","轻小说","经典漫画集","名著漫画","游戏同人作品"]
    ],
    "lay":[
      ["法律"],
      ["民法","经济法","诉讼法/程序法","刑法","商法","行政法","国际法","法律法规","理论法学","法律实务","法律普及读物","外国法律","司法案例","法律随笔","法律工具书","司法制度","法院/检察院","国家法/宪法","法律史","法律文书"]
    ]
  }
}
